tbgutils/__init__.py
tbgutils/dt.py
tbgutils/str.py
tbgutils-1.1.4.dist-info/LICENSE
tbgutils-1.1.4.dist-info/METADATA
tbgutils-1.1.4.dist-info/WHEEL
tbgutils-1.1.4.dist-info/top_level.txt
tbgutils-1.1.4.dist-info/RECORD
