Metadata-Version: 2.1
Name: tbgutils
Version: 1.1.4
Summary: General TBG Utilities
Author-email: Marc Schwarzschild <ms@TheBrookhavenGroup.com>
Maintainer-email: Marc Schwarzschild <ms@TheBrookhavenGroup.com>
License: MIT
Project-URL: homepage, https://github.com/schwarzschild/tbgutils
Project-URL: repository, https://github.com/schwarzschild/tbgutils
Project-URL: documentation, https://github.com/schwarzschild/tbgutils
Keywords: holidays,dates,commify,commitize,cround
Classifier: Topic :: Utilities
Requires-Python: >=3.9
License-File: LICENSE
Requires-Dist: pytz ==2022.7
